{
  "addmm": {
    "0": {
      "LUT": 0.626380706921944,
      "FF": 0.8222876779577811,
      "DSP": 0.044326241134751775,
      "BRAM": 0.0,
      "clock_period_minus_wns": 6.137,
      "LatencyBest": 8973,
      "LatencyAvg": 8973,
      "LatencyWorst": 8973,
      "PipelineII": 8974,
      "elapsed_time": 169.02
    },
    "4": {
      "LUT": 0.6335910652920962,
      "FF": 0.8322210972017673,
      "DSP": 0.1773049645390071,
      "BRAM": 0.0,
      "clock_period_minus_wns": 6.142,
      "LatencyBest": 8781,
      "LatencyAvg": 8781,
      "LatencyWorst": 8781,
      "PipelineII": 8782,
      "elapsed_time": 180.97
    },
    "8": {
      "LUT": 0.6842169857633775,
      "FF": 0.6895096956308296,
      "DSP": 0.3546099290780142,
      "BRAM": 0.0,
      "clock_period_minus_wns": 6.142,
      "LatencyBest": 8749,
      "LatencyAvg": 8749,
      "LatencyWorst": 8749,
      "PipelineII": 8750,
      "elapsed_time": 197.13
    },
    "12": {
      "LUT": 0.816074496809033,
      "FF": 0.8938543200785468,
      "DSP": 0.7092198581560284,
      "BRAM": 0.0,
      "clock_period_minus_wns": 6.409,
      "LatencyBest": 814,
      "LatencyAvg": 814,
      "LatencyWorst": 814,
      "PipelineII": 815,
      "elapsed_time": 175.33
    },
    "16": {
      "LUT": 0.816074496809033,
      "FF": 0.8938543200785468,
      "DSP": 0.7092198581560284,
      "BRAM": 0.0,
      "clock_period_minus_wns": 6.409,
      "LatencyBest": 814,
      "LatencyAvg": 814,
      "LatencyWorst": 814,
      "PipelineII": 815,
      "elapsed_time": 167.7
    },
    "20": {
      "LUT": 1.3863831615120275,
      "FF": 1.0314264236622483,
      "DSP": 2.8368794326241136,
      "BRAM": 0.0,
      "clock_period_minus_wns": 6.409,
      "LatencyBest": 802,
      "LatencyAvg": 802,
      "LatencyWorst": 802,
      "PipelineII": 803,
      "elapsed_time": 203.76
    },
    "24": {
      "LUT": 2.230301914580265,
      "FF": 0.9967169857633774,
      "DSP": 5.673758865248227,
      "BRAM": 0.0,
      "clock_period_minus_wns": 6.409,
      "LatencyBest": 800,
      "LatencyAvg": 800,
      "LatencyWorst": 800,
      "PipelineII": 801,
      "elapsed_time": 217.96
    },
    "28": {
      "LUT": 3.5372944280805103,
      "FF": 1.4620152184585173,
      "DSP": 17.02127659574468,
      "BRAM": 0.0,
      "clock_period_minus_wns": 6.409,
      "LatencyBest": 796,
      "LatencyAvg": 796,
      "LatencyWorst": 796,
      "PipelineII": 797,
      "elapsed_time": 195.05
    },
    "32": {
      "LUT": 3.5372944280805103,
      "FF": 1.4620152184585173,
      "DSP": 17.02127659574468,
      "BRAM": 0.0,
      "clock_period_minus_wns": 6.409,
      "LatencyBest": 796,
      "LatencyAvg": 796,
      "LatencyWorst": 796,
      "PipelineII": 797,
      "elapsed_time": 222.06
    },
    "36": {
      "LUT": 3.6855670103092786,
      "FF": 1.5829421330387825,
      "DSP": 17.02127659574468,
      "BRAM": 0.0,
      "clock_period_minus_wns": 6.142,
      "LatencyBest": 400,
      "LatencyAvg": 400,
      "LatencyWorst": 400,
      "PipelineII": 401,
      "elapsed_time": 403.88
    },
    "40": {
      "LUT": 4.536005768286696,
      "FF": 1.8186978399607268,
      "DSP": 17.02127659574468,
      "BRAM": 0.0,
      "clock_period_minus_wns": 6.419,
      "LatencyBest": 334,
      "LatencyAvg": 334,
      "LatencyWorst": 334,
      "PipelineII": 335,
      "elapsed_time": 323.66
    },
    "1024": {
      "LUT": 4.44986499754541,
      "FF": 1.2794167280314188,
      "DSP": 17.02127659574468,
      "BRAM": 0.0,
      "clock_period_minus_wns": 6.142,
      "LatencyBest": 295,
      "LatencyAvg": 295,
      "LatencyWorst": 295,
      "PipelineII": 296,
      "elapsed_time": 533.68
    }
  },
  "batch_norm": {
    "0": {
      "LUT": 0.27307314678448696,
      "FF": 0.13968151693667158,
      "DSP": 0.598404255319149,
      "BRAM": 0.0,
      "clock_period_minus_wns": 6.056,
      "LatencyBest": 35,
      "LatencyAvg": 35,
      "LatencyWorst": 35,
      "PipelineII": 36,
      "elapsed_time": 81.84
    },
    "4": {
      "LUT": 0.27307314678448696,
      "FF": 0.13968151693667158,
      "DSP": 0.598404255319149,
      "BRAM": 0.0,
      "clock_period_minus_wns": 6.056,
      "LatencyBest": 35,
      "LatencyAvg": 35,
      "LatencyWorst": 35,
      "PipelineII": 36,
      "elapsed_time": 88.59
    },
    "8": {
      "LUT": 0.44075233186057927,
      "FF": 0.19356743986254296,
      "DSP": 1.196808510638298,
      "BRAM": 0.0,
      "clock_period_minus_wns": 6.056,
      "LatencyBest": 28,
      "LatencyAvg": 28,
      "LatencyWorst": 28,
      "PipelineII": 29,
      "elapsed_time": 85.37
    },
    "12": {
      "LUT": 1.8401755031909672,
      "FF": 0.3749002822778596,
      "DSP": 6.382978723404255,
      "BRAM": 0.0,
      "clock_period_minus_wns": 6.056,
      "LatencyBest": 25,
      "LatencyAvg": 25,
      "LatencyWorst": 25,
      "PipelineII": 26,
      "elapsed_time": 130.87
    },
    "16": {
      "LUT": 3.310014727540501,
      "FF": 0.5608738340697104,
      "DSP": 11.96808510638298,
      "BRAM": 0.0,
      "clock_period_minus_wns": 6.056,
      "LatencyBest": 14,
      "LatencyAvg": 14,
      "LatencyWorst": 14,
      "PipelineII": 15,
      "elapsed_time": 81.01
    },
    "20": {
      "LUT": 3.310014727540501,
      "FF": 0.5608738340697104,
      "DSP": 11.96808510638298,
      "BRAM": 0.0,
      "clock_period_minus_wns": 6.056,
      "LatencyBest": 14,
      "LatencyAvg": 14,
      "LatencyWorst": 14,
      "PipelineII": 15,
      "elapsed_time": 72.98
    },
    "24": {
      "LUT": 3.310014727540501,
      "FF": 0.5608738340697104,
      "DSP": 11.96808510638298,
      "BRAM": 0.0,
      "clock_period_minus_wns": 6.056,
      "LatencyBest": 14,
      "LatencyAvg": 14,
      "LatencyWorst": 14,
      "PipelineII": 15,
      "elapsed_time": 77.92
    },
    "28": {
      "LUT": 3.310014727540501,
      "FF": 0.5608738340697104,
      "DSP": 11.96808510638298,
      "BRAM": 0.0,
      "clock_period_minus_wns": 6.056,
      "LatencyBest": 14,
      "LatencyAvg": 14,
      "LatencyWorst": 14,
      "PipelineII": 15,
      "elapsed_time": 80.36
    },
    "32": {
      "LUT": 3.310014727540501,
      "FF": 0.5608738340697104,
      "DSP": 11.96808510638298,
      "BRAM": 0.0,
      "clock_period_minus_wns": 6.056,
      "LatencyBest": 14,
      "LatencyAvg": 14,
      "LatencyWorst": 14,
      "PipelineII": 15,
      "elapsed_time": 79.83
    },
    "36": {
      "LUT": 3.310014727540501,
      "FF": 0.5608738340697104,
      "DSP": 11.96808510638298,
      "BRAM": 0.0,
      "clock_period_minus_wns": 6.056,
      "LatencyBest": 14,
      "LatencyAvg": 14,
      "LatencyWorst": 14,
      "PipelineII": 15,
      "elapsed_time": 73.23
    },
    "40": {
      "LUT": 3.310014727540501,
      "FF": 0.5608738340697104,
      "DSP": 11.96808510638298,
      "BRAM": 0.0,
      "clock_period_minus_wns": 6.056,
      "LatencyBest": 14,
      "LatencyAvg": 14,
      "LatencyWorst": 14,
      "PipelineII": 15,
      "elapsed_time": 72.92
    },
    "1024": {
      "LUT": 3.310014727540501,
      "FF": 0.5608738340697104,
      "DSP": 11.96808510638298,
      "BRAM": 0.0,
      "clock_period_minus_wns": 6.056,
      "LatencyBest": 14,
      "LatencyAvg": 14,
      "LatencyWorst": 14,
      "PipelineII": 15,
      "elapsed_time": 78.0
    }
  },
  "braggnn": {},
  "conv": {
    "0": {
      "LUT": 1.4349380216003926,
      "FF": 0.07536358615611194,
      "DSP": 0.03324468085106383,
      "BRAM": 0.0,
      "clock_period_minus_wns": 6.137,
      "LatencyBest": 11778,
      "LatencyAvg": 11778,
      "LatencyWorst": 11778,
      "PipelineII": 11779,
      "elapsed_time": 327.84
    },
    "4": {
      "LUT": 1.4067869415807561,
      "FF": 0.07532523318605794,
      "DSP": 0.03324468085106383,
      "BRAM": 0.0,
      "clock_period_minus_wns": 6.137,
      "LatencyBest": 11778,
      "LatencyAvg": 11778,
      "LatencyWorst": 11778,
      "PipelineII": 11779,
      "elapsed_time": 316.53
    },
    "8": {
      "LUT": 1.40586647029946,
      "FF": 0.07551699803632794,
      "DSP": 0.03324468085106383,
      "BRAM": 0.0,
      "clock_period_minus_wns": 6.137,
      "LatencyBest": 11778,
      "LatencyAvg": 11778,
      "LatencyWorst": 11778,
      "PipelineII": 11779,
      "elapsed_time": 295.2
    },
    "12": {
      "LUT": 3.6989905498281788,
      "FF": 0.6189018777614138,
      "DSP": 2.183067375886525,
      "BRAM": 0.0,
      "clock_period_minus_wns": 6.142,
      "LatencyBest": 661,
      "LatencyAvg": 661,
      "LatencyWorst": 661,
      "PipelineII": 662,
      "elapsed_time": 473.77
    },
    "16": {
      "LUT": 3.769176485027,
      "FF": 0.6205510554737359,
      "DSP": 2.183067375886525,
      "BRAM": 0.0,
      "clock_period_minus_wns": 6.142,
      "LatencyBest": 661,
      "LatencyAvg": 661,
      "LatencyWorst": 661,
      "PipelineII": 662,
      "elapsed_time": 398.97
    },
    "20": {
      "LUT": 3.769176485027,
      "FF": 0.6205510554737359,
      "DSP": 2.183067375886525,
      "BRAM": 0.0,
      "clock_period_minus_wns": 6.142,
      "LatencyBest": 661,
      "LatencyAvg": 661,
      "LatencyWorst": 661,
      "PipelineII": 662,
      "elapsed_time": 418.81
    },
    "24": {
      "LUT": 4.0355762150220915,
      "FF": 0.6264190598919981,
      "DSP": 2.2717198581560285,
      "BRAM": 0.0,
      "clock_period_minus_wns": 6.142,
      "LatencyBest": 661,
      "LatencyAvg": 661,
      "LatencyWorst": 661,
      "PipelineII": 662,
      "elapsed_time": 455.72
    },
    "28": {
      "LUT": 3.6489015709376535,
      "FF": 0.6189785837015218,
      "DSP": 2.183067375886525,
      "BRAM": 0.0,
      "clock_period_minus_wns": 6.142,
      "LatencyBest": 661,
      "LatencyAvg": 661,
      "LatencyWorst": 661,
      "PipelineII": 662,
      "elapsed_time": 498.03
    },
    "32": {
      "LUT": 4.0586647029946,
      "FF": 0.5340267550319097,
      "DSP": 3.1914893617021276,
      "BRAM": 0.0,
      "clock_period_minus_wns": 6.142,
      "LatencyBest": 61,
      "LatencyAvg": 61,
      "LatencyWorst": 61,
      "PipelineII": 62,
      "elapsed_time": 409.01
    },
    "36": {
      "LUT": 4.025681148748159,
      "FF": 0.5332596956308296,
      "DSP": 3.1914893617021276,
      "BRAM": 0.0,
      "clock_period_minus_wns": 6.143,
      "LatencyBest": 61,
      "LatencyAvg": 61,
      "LatencyWorst": 61,
      "PipelineII": 62,
      "elapsed_time": 407.86
    },
    "40": {
      "LUT": 6.523533382425136,
      "FF": 1.0425487849779087,
      "DSP": 13.031914893617023,
      "BRAM": 0.0,
      "clock_period_minus_wns": 6.166,
      "LatencyBest": 19,
      "LatencyAvg": 19,
      "LatencyWorst": 19,
      "PipelineII": 20,
      "elapsed_time": 334.54
    },
    "1024": {
      "LUT": 6.523533382425136,
      "FF": 1.0425487849779087,
      "DSP": 13.031914893617023,
      "BRAM": 0.0,
      "clock_period_minus_wns": 6.166,
      "LatencyBest": 19,
      "LatencyAvg": 19,
      "LatencyWorst": 19,
      "PipelineII": 20,
      "elapsed_time": 382.4
    }
  },
  "max_pool_2d": {
    "0": {
      "LUT": 0.7254080756013745,
      "FF": 0.42472079037800686,
      "DSP": 0.011081560283687944,
      "BRAM": 0.0,
      "clock_period_minus_wns": 7.401,
      "LatencyBest": 603,
      "LatencyAvg": 603,
      "LatencyWorst": 603,
      "PipelineII": 604,
      "elapsed_time": 167.4
    },
    "4": {
      "LUT": 0.7227233676975945,
      "FF": 0.42472079037800686,
      "DSP": 0.011081560283687944,
      "BRAM": 0.0,
      "clock_period_minus_wns": 7.365,
      "LatencyBest": 603,
      "LatencyAvg": 603,
      "LatencyWorst": 603,
      "PipelineII": 604,
      "elapsed_time": 159.92
    },
    "8": {
      "LUT": 0.8047987236131565,
      "FF": 0.44366715758468334,
      "DSP": 0.011081560283687944,
      "BRAM": 0.0,
      "clock_period_minus_wns": 28.922,
      "LatencyBest": 225,
      "LatencyAvg": 225,
      "LatencyWorst": 225,
      "PipelineII": 226,
      "elapsed_time": 179.81
    },
    "12": {
      "LUT": 0.7786419980363279,
      "FF": 0.44362880461462934,
      "DSP": 0.011081560283687944,
      "BRAM": 0.0,
      "clock_period_minus_wns": 30.42,
      "LatencyBest": 225,
      "LatencyAvg": 225,
      "LatencyWorst": 225,
      "PipelineII": 226,
      "elapsed_time": 163.63
    },
    "16": {
      "LUT": 1.4525036818851251,
      "FF": 0.5965037432498772,
      "DSP": 0.011081560283687944,
      "BRAM": 0.0,
      "clock_period_minus_wns": 70.419,
      "LatencyBest": 171,
      "LatencyAvg": 171,
      "LatencyWorst": 171,
      "PipelineII": 172,
      "elapsed_time": 226.37
    },
    "24": {
      "LUT": 1.7384634266077565,
      "FF": 0.16921330387825234,
      "DSP": 0.011081560283687944,
      "BRAM": 0.0,
      "clock_period_minus_wns": 244.729,
      "LatencyBest": 165,
      "LatencyAvg": 165,
      "LatencyWorst": 165,
      "PipelineII": 166,
      "elapsed_time": 198.6
    },
    "28": {
      "LUT": 1.7384634266077565,
      "FF": 0.16921330387825234,
      "DSP": 0.011081560283687944,
      "BRAM": 0.0,
      "clock_period_minus_wns": 244.729,
      "LatencyBest": 165,
      "LatencyAvg": 165,
      "LatencyWorst": 165,
      "PipelineII": 166,
      "elapsed_time": 193.87
    },
    "32": {
      "LUT": 1.7384634266077565,
      "FF": 0.16921330387825234,
      "DSP": 0.011081560283687944,
      "BRAM": 0.0,
      "clock_period_minus_wns": 244.729,
      "LatencyBest": 165,
      "LatencyAvg": 165,
      "LatencyWorst": 165,
      "PipelineII": 166,
      "elapsed_time": 194.22
    },
    "36": {
      "LUT": 1.7384634266077565,
      "FF": 0.16921330387825234,
      "DSP": 0.011081560283687944,
      "BRAM": 0.0,
      "clock_period_minus_wns": 244.729,
      "LatencyBest": 165,
      "LatencyAvg": 165,
      "LatencyWorst": 165,
      "PipelineII": 166,
      "elapsed_time": 194.27
    },
    "40": {
      "LUT": 1.7384634266077565,
      "FF": 0.16921330387825234,
      "DSP": 0.011081560283687944,
      "BRAM": 0.0,
      "clock_period_minus_wns": 244.729,
      "LatencyBest": 165,
      "LatencyAvg": 165,
      "LatencyWorst": 165,
      "PipelineII": 166,
      "elapsed_time": 207.83
    },
    "1024": {
      "LUT": 1.7384634266077565,
      "FF": 0.16921330387825234,
      "DSP": 0.011081560283687944,
      "BRAM": 0.0,
      "clock_period_minus_wns": 244.729,
      "LatencyBest": 165,
      "LatencyAvg": 165,
      "LatencyWorst": 165,
      "PipelineII": 166,
      "elapsed_time": 202.52
    }
  },
  "soft_max": {
    "0": {
      "LUT": 4.244216372115857,
      "FF": 4.740657216494845,
      "DSP": 0.06648936170212766,
      "BRAM": 0.0,
      "clock_period_minus_wns": 6.615,
      "LatencyBest": 6960,
      "LatencyAvg": 6960,
      "LatencyWorst": 6960,
      "PipelineII": 6961,
      "elapsed_time": 1601.89
    },
    "4": {
      "LUT": 3.910392120765832,
      "FF": 4.787677957781051,
      "DSP": 0.26595744680851063,
      "BRAM": 0.0,
      "clock_period_minus_wns": 6.142,
      "LatencyBest": 3119,
      "LatencyAvg": 3119,
      "LatencyWorst": 3119,
      "PipelineII": 3120,
      "elapsed_time": 1328.68
    },
    "8": {
      "LUT": 4.140740058910162,
      "FF": 4.627477601865489,
      "DSP": 0.5319148936170213,
      "BRAM": 0.0,
      "clock_period_minus_wns": 6.142,
      "LatencyBest": 2351,
      "LatencyAvg": 2351,
      "LatencyWorst": 2351,
      "PipelineII": 2352,
      "elapsed_time": 1729.6
    },
    "12": {
      "LUT": 4.032124447717232,
      "FF": 4.84816059155621,
      "DSP": 1.0638297872340425,
      "BRAM": 0.0,
      "clock_period_minus_wns": 6.142,
      "LatencyBest": 1964,
      "LatencyAvg": 1964,
      "LatencyWorst": 1964,
      "PipelineII": 1965,
      "elapsed_time": 1044.5
    },
    "16": {
      "LUT": 4.032124447717232,
      "FF": 4.84816059155621,
      "DSP": 1.0638297872340425,
      "BRAM": 0.0,
      "clock_period_minus_wns": 6.142,
      "LatencyBest": 1964,
      "LatencyAvg": 1964,
      "LatencyWorst": 1964,
      "PipelineII": 1965,
      "elapsed_time": 1008.08
    },
    "20": {
      "LUT": 6.09605117820324,
      "FF": 5.290945630829651,
      "DSP": 4.25531914893617,
      "BRAM": 0.0,
      "clock_period_minus_wns": 6.142,
      "LatencyBest": 1676,
      "LatencyAvg": 1676,
      "LatencyWorst": 1676,
      "PipelineII": 1677,
      "elapsed_time": 1541.98
    },
    "24": {
      "LUT": 8.725607511045656,
      "FF": 5.359827565046637,
      "DSP": 8.51063829787234,
      "BRAM": 0.0,
      "clock_period_minus_wns": 6.142,
      "LatencyBest": 1628,
      "LatencyAvg": 1628,
      "LatencyWorst": 1628,
      "PipelineII": 1629,
      "elapsed_time": 2509.01
    },
    "28": {
      "LUT": 9.61762088856161,
      "FF": 5.648011782032401,
      "DSP": 17.02127659574468,
      "BRAM": 0.0,
      "clock_period_minus_wns": 6.142,
      "LatencyBest": 1599,
      "LatencyAvg": 1599,
      "LatencyWorst": 1599,
      "PipelineII": 1600,
      "elapsed_time": 1847.87
    },
    "32": {
      "LUT": 9.61762088856161,
      "FF": 5.648011782032401,
      "DSP": 17.02127659574468,
      "BRAM": 0.0,
      "clock_period_minus_wns": 6.142,
      "LatencyBest": 1599,
      "LatencyAvg": 1599,
      "LatencyWorst": 1599,
      "PipelineII": 1600,
      "elapsed_time": 1861.16
    },
    "36": {
      "LUT": 1.2229995090819834,
      "FF": 0.5621011291114384,
      "DSP": 0.26595744680851063,
      "BRAM": 0.0,
      "clock_period_minus_wns": 6.142,
      "LatencyBest": 1556,
      "LatencyAvg": 1556,
      "LatencyWorst": 1556,
      "PipelineII": 1557,
      "elapsed_time": 543.14
    },
    "40": {
      "LUT": 1.2229995090819834,
      "FF": 0.5621011291114384,
      "DSP": 0.26595744680851063,
      "BRAM": 0.0,
      "clock_period_minus_wns": 6.142,
      "LatencyBest": 1556,
      "LatencyAvg": 1556,
      "LatencyWorst": 1556,
      "PipelineII": 1557,
      "elapsed_time": 556.24
    },
    "1024": {
      "LUT": 1.2229995090819834,
      "FF": 0.5621011291114384,
      "DSP": 0.26595744680851063,
      "BRAM": 0.0,
      "clock_period_minus_wns": 6.142,
      "LatencyBest": 1556,
      "LatencyAvg": 1556,
      "LatencyWorst": 1556,
      "PipelineII": 1557,
      "elapsed_time": 556.28
    }
  }
}